LICENSE
MANIFEST.in
README.md
setup.py
mommy_spatial_generators/__init__.py
mommy_spatial_generators/generators.py
mommy_spatial_generators.egg-info/PKG-INFO
mommy_spatial_generators.egg-info/SOURCES.txt
mommy_spatial_generators.egg-info/dependency_links.txt
mommy_spatial_generators.egg-info/requires.txt
mommy_spatial_generators.egg-info/top_level.txt