Metadata-Version: 1.0
Name: mommy-spatial-generators
Version: 0.1.2
Summary: Spatial generators for model mommy. This enables you to generate dummy values for GeoDjango fields.
Home-page: http://www.sigmageosistemas.com.br
Author: George Silva
Author-email: george@consultoriasigma.com.br
License: Apache 2.0
Platform: UNKNOWN
Classifier: Environment :: Web Environment
Classifier: Framework :: Django
Classifier: Intended Audience :: Developers
Classifier: Operating System :: OS Independent
Classifier: Programming Language :: Python
Classifier: Programming Language :: Python :: 2.7
Classifier: Programming Language :: Python :: 3
Classifier: Topic :: Internet :: WWW/HTTP
Classifier: Topic :: Internet :: WWW/HTTP :: Dynamic Content
